rallyplot/__init__.py
rallyplot/librallyplot.so
rallyplot/plotter.py
rallyplot/pythonBindings.cpython-310-x86_64-linux-gnu.so
rallyplot/pythonBindings.cpython-311-x86_64-linux-gnu.so
rallyplot/pythonBindings.cpython-312-x86_64-linux-gnu.so
rallyplot/plugins/egldeviceintegrations/libqeglfs-emu-integration.so
rallyplot/plugins/egldeviceintegrations/libqeglfs-kms-egldevice-integration.so
rallyplot/plugins/egldeviceintegrations/libqeglfs-kms-integration.so
rallyplot/plugins/egldeviceintegrations/libqeglfs-x11-integration.so
rallyplot/plugins/generic/libqevdevkeyboardplugin.so
rallyplot/plugins/generic/libqevdevmouseplugin.so
rallyplot/plugins/generic/libqevdevtabletplugin.so
rallyplot/plugins/generic/libqevdevtouchplugin.so
rallyplot/plugins/generic/libqtuiotouchplugin.so
rallyplot/plugins/platforms/libqeglfs.so
rallyplot/plugins/platforms/libqlinuxfb.so
rallyplot/plugins/platforms/libqminimal.so
rallyplot/plugins/platforms/libqminimalegl.so
rallyplot/plugins/platforms/libqoffscreen.so
rallyplot/plugins/platforms/libqvkkhrdisplay.so
rallyplot/plugins/platforms/libqvnc.so
rallyplot/plugins/platforms/libqwayland-egl.so
rallyplot/plugins/platforms/libqwayland-generic.so
rallyplot/plugins/platforms/libqxcb.so
rallyplot/plugins/wayland-decoration-client/libadwaita.so
rallyplot/plugins/wayland-decoration-client/libbradient.so
rallyplot/plugins/wayland-graphics-integration-client/libdmabuf-server.so
rallyplot/plugins/wayland-graphics-integration-client/libdrm-egl-server.so
rallyplot/plugins/wayland-graphics-integration-client/libqt-plugin-wayland-egl.so
rallyplot/plugins/wayland-graphics-integration-client/libshm-emulation-server.so
rallyplot/plugins/wayland-graphics-integration-client/libvulkan-server.so
rallyplot/plugins/wayland-shell-integration/libfullscreen-shell-v1.so
rallyplot/plugins/wayland-shell-integration/libivi-shell.so
rallyplot/plugins/wayland-shell-integration/libqt-shell.so
rallyplot-0.0.0rc5.dist-info/METADATA
rallyplot-0.0.0rc5.dist-info/WHEEL
rallyplot-0.0.0rc5.dist-info/RECORD
rallyplot-0.0.0rc5.dist-info/licenses/LICENSE
rallyplot-0.0.0rc5.dist-info/sboms/auditwheel.cdx.json
