Metadata-Version: 2.2
Name: rallyplot
Version: 0.0.0rc5
Summary: Fast finance plots on the graphics card.
License:                     GNU AFFERO GENERAL PUBLIC LICENSE
Classifier: Programming Language :: Python
Classifier: Programming Language :: Python :: 3.10
Classifier: Programming Language :: Python :: 3.11
Classifier: Programming Language :: Python :: 3.12
Classifier: Programming Language :: Python :: 3.13
Classifier: Operating System :: OS Independent
Classifier: License :: OSI Approved :: GNU Affero General Public License v3 or later (AGPLv3+)
Requires-Python: >=3.10
Requires-Dist: numpy
Requires-Dist: pandas
Provides-Extra: dev
Requires-Dist: matplotlib; extra == "dev"
Requires-Dist: aqtinstall; extra == "dev"
